exa/__init__.py
exa/cluster_init.py
exa/structs/__init__.py
exa/structs/hive_model.py
exa/structs/model_thread_router.py
exa/structs/parallelize_models_gpus.py
exa/utils/__init__.py
exa/utils/all_reduce.py
exa/utils/count_cores_for_workers.py
exa/utils/dist_process_init.py
exa/utils/fused_all_gather.py
exa/utils/gpu_ops.py
exxa-0.6.4.dist-info/LICENSE
exxa-0.6.4.dist-info/WHEEL
exxa-0.6.4.dist-info/entry_points.txt
exxa-0.6.4.dist-info/METADATA
exxa-0.6.4.dist-info/RECORD
