Metadata-Version: 2.1
Name: exxa
Version: 0.6.4
Summary: Exa - Pytorch
Home-page: https://github.com/kyegomez/Exa
License: MIT
Keywords: artificial intelligence,deep learning,optimizers,Prompt Engineering
Author: Kye Gomez
Author-email: kye@apac.ai
Requires-Python: >=3.10,<4.0
Classifier: Development Status :: 4 - Beta
Classifier: Intended Audience :: Developers
Classifier: License :: OSI Approved :: MIT License
Classifier: Programming Language :: Python :: 3
Classifier: Programming Language :: Python :: 3.10
Classifier: Programming Language :: Python :: 3.11
Classifier: Programming Language :: Python :: 3.6
Classifier: Topic :: Scientific/Engineering :: Artificial Intelligence
Requires-Dist: loguru (>=0.5.3,<0.6.0)
Requires-Dist: torch (>2.0.0)
Project-URL: Documentation, https://github.com/kyegomez/Exa
Project-URL: Repository, https://github.com/kyegomez/Exa
